AUTHORS.rst
CONTRIBUTING.rst
HISTORY.rst
LICENSE
MANIFEST.in
README.rst
setup.cfg
setup.py
docs/Makefile
docs/authors.rst
docs/conf.py
docs/contributing.rst
docs/history.rst
docs/index.rst
docs/installation.rst
docs/make.bat
docs/readme.rst
docs/usage.rst
scriptqualis/__init__.py
scriptqualis/scriptqualis.py
scriptqualis.egg-info/PKG-INFO
scriptqualis.egg-info/SOURCES.txt
scriptqualis.egg-info/dependency_links.txt
scriptqualis.egg-info/not-zip-safe
scriptqualis.egg-info/top_level.txt
tests/__init__.py
tests/test_scriptqualis.py