Metadata-Version: 1.1
Name: scriptqualis
Version: 0.1.0
Summary: Ferramenta para extrair informações do Qualis CAPES e as salvar localmente.
Home-page: https://bitbucket.org/scriptlattes/scriptqualis
Author: Fabio Natanael Kepler
Author-email: fabio@kepler.pro.br
License: BSD
Keywords: scriptqualis
Platform: UNKNOWN
Classifier: Development Status :: 2 - Pre-Alpha
Classifier: Intended Audience :: Developers
Classifier: License :: OSI Approved :: BSD License
Classifier: Natural Language :: Portuguese
Classifier: Programming Language :: Python :: 2
Classifier: Programming Language :: Python :: 2.7
Classifier: Programming Language :: Python :: 3
Classifier: Programming Language :: Python :: 3.4
